{
  "id": "273530fd-479b-40f2-a7ca-4abea5e78817",
  "prevId": "00000000-0000-0000-0000-000000000000",
  "version": "7",
  "dialect": "REMOVEDql",
  "tables": {
    "public.korisnik": {
      "name": "korisnik",
      "schema": "",
      "columns": {
        "id": {
          "name": "id",
          "type": "uuid",
          "primaryKey": true,
          "notNull": true,
          "default": "gen_random_uuid()"
        },
        "ime": {
          "name": "ime",
          "type": "varchar(100)",
          "primaryKey": false,
          "notNull": true
        },
        "prezime": {
          "name": "prezime",
          "type": "varchar(100)",
          "primaryKey": false,
          "notNull": true
        },
        "email": {
          "name": "email",
          "type": "varchar(255)",
          "primaryKey": false,
          "notNull": true
        },
        "lozinka": {
          "name": "lozinka",
          "type": "varchar(255)",
          "primaryKey": false,
          "notNull": true
        },
        "uloga": {
          "name": "uloga",
          "type": "uloga",
          "typeSchema": "public",
          "primaryKey": false,
          "notNull": true
        }
      },
      "indexes": {},
      "foreignKeys": {},
      "compositePrimaryKeys": {},
      "uniqueConstraints": {
        "korisnik_email_unique": {
          "name": "korisnik_email_unique",
          "nullsNotDistinct": false,
          "columns": [
            "email"
          ]
        }
      },
      "policies": {},
      "checkConstraints": {},
      "isRLSEnabled": false
    }
  },
  "enums": {
    "public.uloga": {
      "name": "uloga",
      "schema": "public",
      "values": [
        "ADMIN",
        "KLIJENT",
        "EDUKATOR"
      ]
    }
  },
  "schemas": {},
  "sequences": {},
  "roles": {},
  "policies": {},
  "views": {},
  "_meta": {
    "columns": {},
    "schemas": {},
    "tables": {}
  }
}